{
    "state": "warDay",
    "war_end_time": "20200811T104147.606Z",
    "collection_end_time": null,
    "clan": {
        "tag": "#LP98YUCV",
        "name": "Abuzement Park",
        "badge_id": 16000003,
        "clan_score": 2889,
        "participants": 25,
        "crowns": 16,
        "battles_remaining": null,
        "battles_played": 11,
        "wins": 7
    },
    "participants": [
        {
            "tag": "#JRG8G8LL",
            "name": "Evan_Wibb",
            "cards_earned": 1400,
            "battles_played": 0,
            "collection_day_battles_played": 3,
            "wins": 0,
            "number_of_battles": 1
        },
        {
            "tag": "#2Y02UG8C8",
            "name": "Rascal09",
            "cards_earned": 1400,
            "battles_played": 0,
            "collection_day_battles_played": 3,
            "wins": 0,
            "number_of_battles": 1
        },
        {
            "tag": "#2YUGR2P99",
            "name": "\ud5ff\ub808\ud5e4\ud5e4",
            "cards_earned": 297,
            "battles_played": 0,
            "collection_day_battles_played": 1,
            "wins": 0,
            "number_of_battles": 1
        },
        {
            "tag": "#Y2C2RQG9R",
            "name": "kr21__",
            "cards_earned": 1400,
            "battles_played": 0,
            "collection_day_battles_played": 3,
            "wins": 0,
            "number_of_battles": 1
        },
        {
            "tag": "#PV02PGVQ",
            "name": "someone",
            "cards_earned": 1120,
            "battles_played": 0,
            "collection_day_battles_played": 2,
            "wins": 0,
            "number_of_battles": 1
        },
        {
            "tag": "#QGLYUPYJ",
            "name": "VB2",
            "cards_earned": 1120,
            "battles_played": 0,
            "collection_day_battles_played": 3,
            "wins": 0,
            "number_of_battles": 1
        },
        {
            "tag": "#8VLL2QL8P",
            "name": "climaxspot",
            "cards_earned": 840,
            "battles_played": 0,
            "collection_day_battles_played": 3,
            "wins": 0,
            "number_of_battles": 1
        },
        {
            "tag": "#J8CGQRJY",
            "name": "CaptAwhole",
            "cards_earned": 1487,
            "battles_played": 0,
            "collection_day_battles_played": 3,
            "wins": 0,
            "number_of_battles": 1
        },
        {
            "tag": "#8RQYURC",
            "name": "Tranosaurus",
            "cards_earned": 1120,
            "battles_played": 0,
            "collection_day_battles_played": 3,
            "wins": 0,
            "number_of_battles": 1
        },
        {
            "tag": "#9P0V20CY8",
            "name": "Hilda",
            "cards_earned": 1400,
            "battles_played": 0,
            "collection_day_battles_played": 3,
            "wins": 0,
            "number_of_battles": 1
        },
        {
            "tag": "#QRGULUJRL",
            "name": "Gaviii",
            "cards_earned": 280,
            "battles_played": 0,
            "collection_day_battles_played": 1,
            "wins": 0,
            "number_of_battles": 1
        },
        {
            "tag": "#UVGUUVC0",
            "name": "ok guy",
            "cards_earned": 891,
            "battles_played": 0,
            "collection_day_battles_played": 3,
            "wins": 0,
            "number_of_battles": 1
        },
        {
            "tag": "#CLL8Q09",
            "name": "Wub",
            "cards_earned": 280,
            "battles_played": 0,
            "collection_day_battles_played": 1,
            "wins": 0,
            "number_of_battles": 1
        },
        {
            "tag": "#QYVQ0RUUL",
            "name": "tim",
            "cards_earned": 1120,
            "battles_played": 0,
            "collection_day_battles_played": 2,
            "wins": 0,
            "number_of_battles": 1
        },
        {
            "tag": "#YRJLYVJG",
            "name": "FlashJakson",
            "cards_earned": 1120,
            "battles_played": 1,
            "collection_day_battles_played": 3,
            "wins": 1,
            "number_of_battles": 1
        },
        {
            "tag": "#J28UPQ0P",
            "name": "didthrashersmom",
            "cards_earned": 1189,
            "battles_played": 1,
            "collection_day_battles_played": 3,
            "wins": 0,
            "number_of_battles": 1
        },
        {
            "tag": "#2VQUL0UUG",
            "name": "Master Zakuri",
            "cards_earned": 1189,
            "battles_played": 1,
            "collection_day_battles_played": 3,
            "wins": 1,
            "number_of_battles": 1
        },
        {
            "tag": "#YLCLYCCLR",
            "name": "yggdrasil",
            "cards_earned": 1120,
            "battles_played": 1,
            "collection_day_battles_played": 3,
            "wins": 0,
            "number_of_battles": 1
        },
        {
            "tag": "#8YRYRG0G",
            "name": "Blobby",
            "cards_earned": 1487,
            "battles_played": 1,
            "collection_day_battles_played": 3,
            "wins": 1,
            "number_of_battles": 1
        },
        {
            "tag": "#CV29GC9",
            "name": "Srgt_Atrex",
            "cards_earned": 1680,
            "battles_played": 1,
            "collection_day_battles_played": 3,
            "wins": 1,
            "number_of_battles": 1
        },
        {
            "tag": "#YLGUQRVVQ",
            "name": "Granteli",
            "cards_earned": 1487,
            "battles_played": 1,
            "collection_day_battles_played": 3,
            "wins": 1,
            "number_of_battles": 1
        },
        {
            "tag": "#8GUQLCGR",
            "name": "the Batman",
            "cards_earned": 1120,
            "battles_played": 1,
            "collection_day_battles_played": 3,
            "wins": 1,
            "number_of_battles": 1
        },
        {
            "tag": "#899LR9Y80",
            "name": "Warlord",
            "cards_earned": 840,
            "battles_played": 1,
            "collection_day_battles_played": 3,
            "wins": 0,
            "number_of_battles": 1
        },
        {
            "tag": "#9QG9Q8CVG",
            "name": "Hambone",
            "cards_earned": 1400,
            "battles_played": 1,
            "collection_day_battles_played": 3,
            "wins": 1,
            "number_of_battles": 1
        },
        {
            "tag": "#Y99CRCGUC",
            "name": "toxos",
            "cards_earned": 1120,
            "battles_played": 1,
            "collection_day_battles_played": 3,
            "wins": 0,
            "number_of_battles": 1
        }
    ],
    "clans": [
        {
            "tag": "#PCLV0G2V",
            "name": "\uff36\uff21\uff34\uff21\uff2e \u26a1",
            "badge_id": 16000030,
            "clan_score": 2988,
            "participants": 25,
            "crowns": 17,
            "battles_remaining": 15,
            "battles_played": 10,
            "wins": 8
        },
        {
            "tag": "#PJ8GQLUR",
            "name": "caminantes 2.0",
            "badge_id": 16000172,
            "clan_score": 2436,
            "participants": 24,
            "crowns": 5,
            "battles_remaining": 6,
            "battles_played": 18,
            "wins": 3
        },
        {
            "tag": "#22YG0PGY",
            "name": ".+\u203b+.\u8c6c\u4ed4\u6c34\u6676\u5bae.+\u203b+.",
            "badge_id": 16000131,
            "clan_score": 2925,
            "participants": 25,
            "crowns": 11,
            "battles_remaining": 11,
            "battles_played": 14,
            "wins": 10
        },
        {
            "tag": "#PLUJ00RQ",
            "name": "BritishNProud",
            "badge_id": 16000029,
            "clan_score": 2953,
            "participants": 25,
            "crowns": 5,
            "battles_remaining": 12,
            "battles_played": 13,
            "wins": 1
        },
        {
            "tag": "#LP98YUCV",
            "name": "Abuzement Park",
            "badge_id": 16000003,
            "clan_score": 2889,
            "participants": 25,
            "crowns": 16,
            "battles_remaining": 14,
            "battles_played": 11,
            "wins": 7
        }
    ]
}