[
    {
        "clan": {
            "tag": "#LP98YUCV",
            "name": "Abuzement Park",
            "badge_id": 16000003,
            "clan_score": 582,
            "participants": 22,
            "battles_played": 21,
            "wins": 7,
            "crowns": 18
        },
        "trophy_change": -8
    },
    {
        "clan": {
            "tag": "#LP98YUCV",
            "name": "Abuzement Park",
            "badge_id": 16000003,
            "clan_score": 590,
            "participants": 18,
            "battles_played": 22,
            "wins": 14,
            "crowns": 37
        },
        "trophy_change": 114
    },
    {
        "clan": {
            "tag": "#LP98YUCV",
            "name": "Abuzement Park",
            "badge_id": 16000003,
            "clan_score": 476,
            "participants": 18,
            "battles_played": 19,
            "wins": 8,
            "crowns": 22
        },
        "trophy_change": 58
    },
    {
        "clan": {
            "tag": "#LP98YUCV",
            "name": "Abuzement Park",
            "badge_id": 16000003,
            "clan_score": 418,
            "participants": 19,
            "battles_played": 22,
            "wins": 15,
            "crowns": 33
        },
        "trophy_change": 115
    },
    {
        "clan": {
            "tag": "#LP98YUCV",
            "name": "Abuzement Park",
            "badge_id": 16000003,
            "clan_score": 303,
            "participants": 19,
            "battles_played": 20,
            "wins": 12,
            "crowns": 27
        },
        "trophy_change": 62
    },
    {
        "clan": {
            "tag": "#LP98YUCV",
            "name": "Abuzement Park",
            "badge_id": 16000003,
            "clan_score": 241,
            "participants": 20,
            "battles_played": 21,
            "wins": 6,
            "crowns": 12
        },
        "trophy_change": -14
    },
    {
        "clan": {
            "tag": "#LP98YUCV",
            "name": "Abuzement Park",
            "badge_id": 16000003,
            "clan_score": 255,
            "participants": 16,
            "battles_played": 16,
            "wins": 5,
            "crowns": 11
        },
        "trophy_change": -15
    },
    {
        "clan": {
            "tag": "#LP98YUCV",
            "name": "Abuzement Park",
            "badge_id": 16000003,
            "clan_score": 270,
            "participants": 19,
            "battles_played": 18,
            "wins": 9,
            "crowns": 18
        },
        "trophy_change": 4
    },
    {
        "clan": {
            "tag": "#LP98YUCV",
            "name": "Abuzement Park",
            "badge_id": 16000003,
            "clan_score": 266,
            "participants": 17,
            "battles_played": 20,
            "wins": 6,
            "crowns": 17
        },
        "trophy_change": -14
    },
    {
        "clan": {
            "tag": "#LP98YUCV",
            "name": "Abuzement Park",
            "badge_id": 16000003,
            "clan_score": 280,
            "participants": 16,
            "battles_played": 17,
            "wins": 8,
            "crowns": 22
        },
        "trophy_change": 108
    }
]